LICENSE.txt
README.md
meanwhile.py
setup.cfg
setup.py
meanwhile.egg-info/PKG-INFO
meanwhile.egg-info/SOURCES.txt
meanwhile.egg-info/dependency_links.txt
meanwhile.egg-info/top_level.txt