Metadata-Version: 2.1
Name: meanwhile
Version: 1.1.1
Summary: Very easy multithreading
Home-page: https://github.com/hagai-helman/meanwhile
Author: Hagai Helman Tov
Author-email: hagai.helman@gmail.com
License: MIT
Keywords: threading,threads,multithreading
Classifier: Development Status :: 5 - Production/Stable
Classifier: License :: OSI Approved :: MIT License
Classifier: Intended Audience :: Developers
Classifier: Programming Language :: Python :: 3
Requires-Python: >=3.6
License-File: LICENSE.txt
